{"_default": {"1": {"kuerzel": "CROBTC", "aa_Tag": "2020-02-21", "fullName": "CROBTC", "close": 6.002e-06, "volume": 6184605.1}, "2": {"kuerzel": "CROBTC", "aa_Tag": "2020-02-22", "fullName": "CROBTC", "close": 6.193e-06, "volume": 12499457.8}, "3": {"kuerzel": "CROBTC", "aa_Tag": "2020-02-23", "fullName": "CROBTC", "close": 6.234e-06, "volume": 12243236.7}, "4": {"kuerzel": "CROBTC", "aa_Tag": "2020-02-24", "fullName": "CROBTC", "close": 6.23e-06, "volume": 7029801.6}, "5": {"kuerzel": "CROBTC", "aa_Tag": "2020-02-25", "fullName": "CROBTC", "close": 6.348e-06, "volume": 3229178.0}, "6": {"kuerzel": "CROBTC", "aa_Tag": "2020-02-26", "fullName": "CROBTC", "close": 6.028e-06, "volume": 2458397.5}, "7": {"kuerzel": "CROBTC", "aa_Tag": "2020-02-27", "fullName": "CROBTC", "close": 6.06e-06, "volume": 1298748.4}, "8": {"kuerzel": "CROBTC", "aa_Tag": "2020-02-28", "fullName": "CROBTC", "close": 6.134e-06, "volume": 2678817.3}, "9": {"kuerzel": "CROBTC", "aa_Tag": "2020-02-29", "fullName": "CROBTC", "close": 6.132e-06, "volume": 2453847.0}, "10": {"kuerzel": "CROBTC", "aa_Tag": "2020-03-01", "fullName": "CROBTC", "close": 6.212e-06, "volume": 1296810.3}, "11": {"kuerzel": "CROBTC", "aa_Tag": "2020-03-02", "fullName": "CROBTC", "close": 6.209e-06, "volume": 3567943.2}, "12": {"kuerzel": "CROBTC", "aa_Tag": "2020-03-03", "fullName": "CROBTC", "close": 6.475e-06, "volume": 3599598.6}, "13": {"kuerzel": "CROBTC", "aa_Tag": "2020-03-04", "fullName": "CROBTC", "close": 6.536e-06, "volume": 2121468.3}, "14": {"kuerzel": "CROBTC", "aa_Tag": "2020-03-05", "fullName": "CROBTC", "close": 6.366e-06, "volume": 2839565.2}, "15": {"kuerzel": "CROBTC", "aa_Tag": "2020-03-06", "fullName": "CROBTC", "close": 6.342e-06, "volume": 1405314.9}, "16": {"kuerzel": "CROBTC", "aa_Tag": "2020-03-07", "fullName": "CROBTC", "close": 6.314e-06, "volume": 1509909.2}, "17": {"kuerzel": "CROBTC", "aa_Tag": "2020-03-08", "fullName": "CROBTC", "close": 6.277e-06, "volume": 889276.2}, "18": {"kuerzel": "CROBTC", "aa_Tag": "2020-03-09", "fullName": "CROBTC", "close": 6.303e-06, "volume": 2103457.4}, "19": {"kuerzel": "CROBTC", "aa_Tag": "2020-03-10", "fullName": "CROBTC", "close": 6.273e-06, "volume": 3201703.4}, "20": {"kuerzel": "CROBTC", "aa_Tag": "2020-03-11", "fullName": "CROBTC", "close": 6.267e-06, "volume": 9233759.1}, "21": {"kuerzel": "CROBTC", "aa_Tag": "2020-03-12", "fullName": "CROBTC", "close": 6.221e-06, "volume": 9185624.8}, "22": {"kuerzel": "CROBTC", "aa_Tag": "2020-03-13", "fullName": "CROBTC", "close": 6.223e-06, "volume": 14178047.0}, "23": {"kuerzel": "CROBTC", "aa_Tag": "2020-03-14", "fullName": "CROBTC", "close": 6.189e-06, "volume": 1919584.8}, "24": {"kuerzel": "CROBTC", "aa_Tag": "2020-03-15", "fullName": "CROBTC", "close": 6.023e-06, "volume": 2470780.9}, "25": {"kuerzel": "CROBTC", "aa_Tag": "2020-03-16", "fullName": "CROBTC", "close": 6.246e-06, "volume": 1577963.2}, "26": {"kuerzel": "CROBTC", "aa_Tag": "2020-03-17", "fullName": "CROBTC", "close": 6.543e-06, "volume": 4750455.0}, "27": {"kuerzel": "CROBTC", "aa_Tag": "2020-03-18", "fullName": "CROBTC", "close": 6.633e-06, "volume": 2620548.8}, "28": {"kuerzel": "CROBTC", "aa_Tag": "2020-03-19", "fullName": "CROBTC", "close": 6.402e-06, "volume": 3358316.6}, "29": {"kuerzel": "CROBTC", "aa_Tag": "2020-03-20", "fullName": "CROBTC", "close": 6.302e-06, "volume": 4111157.5}, "30": {"kuerzel": "CROBTC", "aa_Tag": "2020-03-21", "fullName": "CROBTC", "close": 6.191e-06, "volume": 2272836.8}, "31": {"kuerzel": "CROBTC", "aa_Tag": "2020-03-22", "fullName": "CROBTC", "close": 6.206e-06, "volume": 1390761.8}, "32": {"kuerzel": "CROBTC", "aa_Tag": "2020-03-23", "fullName": "CROBTC", "close": 6.401e-06, "volume": 1705661.5}, "33": {"kuerzel": "CROBTC", "aa_Tag": "2020-03-24", "fullName": "CROBTC", "close": 6.472e-06, "volume": 3241240.3}, "34": {"kuerzel": "CROBTC", "aa_Tag": "2020-03-25", "fullName": "CROBTC", "close": 6.538e-06, "volume": 2246226.7}, "35": {"kuerzel": "CROBTC", "aa_Tag": "2020-03-26", "fullName": "CROBTC", "close": 6.801e-06, "volume": 1809091.6}, "36": {"kuerzel": "CROBTC", "aa_Tag": "2020-03-27", "fullName": "CROBTC", "close": 6.957e-06, "volume": 1667809.2}, "37": {"kuerzel": "CROBTC", "aa_Tag": "2020-03-28", "fullName": "CROBTC", "close": 6.741e-06, "volume": 2038753.1}, "38": {"kuerzel": "CROBTC", "aa_Tag": "2020-03-29", "fullName": "CROBTC", "close": 7.055e-06, "volume": 1459657.7}, "39": {"kuerzel": "CROBTC", "aa_Tag": "2020-03-30", "fullName": "CROBTC", "close": 7.49e-06, "volume": 1949591.3}, "40": {"kuerzel": "CROBTC", "aa_Tag": "2020-03-31", "fullName": "CROBTC", "close": 7.653e-06, "volume": 921859.6}, "41": {"kuerzel": "CROBTC", "aa_Tag": "2020-04-01", "fullName": "CROBTC", "close": 7.467e-06, "volume": 1432123.7}, "42": {"kuerzel": "CROBTC", "aa_Tag": "2020-04-02", "fullName": "CROBTC", "close": 7.17e-06, "volume": 1213855.0}, "43": {"kuerzel": "CROBTC", "aa_Tag": "2020-04-03", "fullName": "CROBTC", "close": 7.035e-06, "volume": 2321046.2}, "44": {"kuerzel": "CROBTC", "aa_Tag": "2020-04-04", "fullName": "CROBTC", "close": 7.004e-06, "volume": 3570250.1}, "45": {"kuerzel": "CROBTC", "aa_Tag": "2020-04-05", "fullName": "CROBTC", "close": 7.181e-06, "volume": 2686551.3}, "46": {"kuerzel": "CROBTC", "aa_Tag": "2020-04-06", "fullName": "CROBTC", "close": 7.26e-06, "volume": 3517245.9}, "47": {"kuerzel": "CROBTC", "aa_Tag": "2020-04-07", "fullName": "CROBTC", "close": 7.163e-06, "volume": 3580258.7}, "48": {"kuerzel": "CROBTC", "aa_Tag": "2020-04-08", "fullName": "CROBTC", "close": 7.392e-06, "volume": 2454407.1}, "49": {"kuerzel": "CROBTC", "aa_Tag": "2020-04-09", "fullName": "CROBTC", "close": 7.251e-06, "volume": 1588571.2}, "50": {"kuerzel": "CROBTC", "aa_Tag": "2020-04-10", "fullName": "CROBTC", "close": 7.284e-06, "volume": 1343770.8}, "51": {"kuerzel": "CROBTC", "aa_Tag": "2020-04-11", "fullName": "CROBTC", "close": 7.187e-06, "volume": 1749693.3}, "52": {"kuerzel": "CROBTC", "aa_Tag": "2020-04-12", "fullName": "CROBTC", "close": 7.207e-06, "volume": 3953837.7}, "53": {"kuerzel": "CROBTC", "aa_Tag": "2020-04-13", "fullName": "CROBTC", "close": 7.178e-06, "volume": 2475197.0}, "54": {"kuerzel": "CROBTC", "aa_Tag": "2020-04-14", "fullName": "CROBTC", "close": 7.338e-06, "volume": 1522442.4}, "55": {"kuerzel": "CROBTC", "aa_Tag": "2020-04-15", "fullName": "CROBTC", "close": 7.3e-06, "volume": 501771.8}, "56": {"kuerzel": "CROBTC", "aa_Tag": "2020-04-16", "fullName": "CROBTC", "close": 7.143e-06, "volume": 1220232.4}, "57": {"kuerzel": "CROBTC", "aa_Tag": "2020-04-17", "fullName": "CROBTC", "close": 7.113e-06, "volume": 3283205.2}, "58": {"kuerzel": "CROBTC", "aa_Tag": "2020-04-18", "fullName": "CROBTC", "close": 7.134e-06, "volume": 1957436.5}, "59": {"kuerzel": "CROBTC", "aa_Tag": "2020-04-19", "fullName": "CROBTC", "close": 7.057e-06, "volume": 1061892.3}, "60": {"kuerzel": "CROBTC", "aa_Tag": "2020-04-20", "fullName": "CROBTC", "close": 7.046e-06, "volume": 1226351.9}, "61": {"kuerzel": "CROBTC", "aa_Tag": "2020-04-21", "fullName": "CROBTC", "close": 7.068e-06, "volume": 3462801.1}, "62": {"kuerzel": "CROBTC", "aa_Tag": "2020-04-22", "fullName": "CROBTC", "close": 7.096e-06, "volume": 4987222.3}, "63": {"kuerzel": "CROBTC", "aa_Tag": "2020-04-23", "fullName": "CROBTC", "close": 7.03e-06, "volume": 3499895.5}, "64": {"kuerzel": "CROBTC", "aa_Tag": "2020-04-24", "fullName": "CROBTC", "close": 7.047e-06, "volume": 669757.7}, "65": {"kuerzel": "CROBTC", "aa_Tag": "2020-04-25", "fullName": "CROBTC", "close": 7.042e-06, "volume": 1397894.4}, "66": {"kuerzel": "CROBTC", "aa_Tag": "2020-04-26", "fullName": "CROBTC", "close": 7.193e-06, "volume": 947502.6}, "67": {"kuerzel": "CROBTC", "aa_Tag": "2020-04-27", "fullName": "CROBTC", "close": 7.197e-06, "volume": 3093649.6}, "68": {"kuerzel": "CROBTC", "aa_Tag": "2020-04-28", "fullName": "CROBTC", "close": 7.247e-06, "volume": 4306895.5}, "69": {"kuerzel": "CROBTC", "aa_Tag": "2020-04-29", "fullName": "CROBTC", "close": 7.172e-06, "volume": 6143300.3}, "70": {"kuerzel": "CROBTC", "aa_Tag": "2020-04-30", "fullName": "CROBTC", "close": 6.962e-06, "volume": 3727048.2}}}